pyProBound/MotifCentral.v1.0.0.json
pyProBound/ProBound-jar-with-dependencies.jar
pyProBound/__init__.py
pyProBound/database.py
pyProBound/schema.builder.json
pyProBound/schema.config.json
pyProBound/schema.general.json
pyProBound/schema.output.json
pyProBound/scoring.py
pyprobound-0.0.14.dist-info/LICENSE
pyprobound-0.0.14.dist-info/METADATA
pyprobound-0.0.14.dist-info/WHEEL
pyprobound-0.0.14.dist-info/top_level.txt
pyprobound-0.0.14.dist-info/RECORD
