Metadata-Version: 2.1
Name: pyprobound
Version: 0.0.14
Summary: ProBound model manipulation and scoring interface
Author-email: Katerina Faltejskova <katerina.faltejskova@uochb.cas.cz>
Project-URL: repository, https://github.com/Caeph/pyProBound
License-File: LICENSE
Requires-Dist: pyjnius
Requires-Dist: swifter
Requires-Dist: numpy
Requires-Dist: pandas
